{"nodes": [{"id": "users_mohdsaeedafri_all_code_base_ems_swagger_testing_guide_md", "label": "SWAGGER_TESTING_GUIDE.md", "file_type": "document", "source_file": "SWAGGER_TESTING_GUIDE.md", "source_location": "L1"}, {"id": "ems_swagger_testing_guide_ems_swagger_testing_guide", "label": "EMS Swagger Testing Guide", "file_type": "document", "source_file": "SWAGGER_TESTING_GUIDE.md", "source_location": "L1"}, {"id": "ems_swagger_testing_guide_test_result_production_verified_2026_05_19", "label": "Test result (production, verified 2026-05-19)", "file_type": "document", "source_file": "SWAGGER_TESTING_GUIDE.md", "source_location": "L9"}, {"id": "ems_swagger_testing_guide_part_a_the_2_step_auth_flow_new_simpler", "label": "Part A \u2014 The 2-Step Auth Flow (NEW, simpler)", "file_type": "document", "source_file": "SWAGGER_TESTING_GUIDE.md", "source_location": "L22"}, {"id": "ems_swagger_testing_guide_step_1_open_swagger_ui", "label": "Step 1 \u2014 Open Swagger UI", "file_type": "document", "source_file": "SWAGGER_TESTING_GUIDE.md", "source_location": "L26"}, {"id": "ems_swagger_testing_guide_step_2_find_post_auth_login_and_click_it_to_expand", "label": "Step 2 \u2014 Find `POST /auth/login` and click it to expand", "file_type": "document", "source_file": "SWAGGER_TESTING_GUIDE.md", "source_location": "L32"}, {"id": "ems_swagger_testing_guide_step_3_click_try_it_out", "label": "Step 3 \u2014 Click \"Try it out\"", "file_type": "document", "source_file": "SWAGGER_TESTING_GUIDE.md", "source_location": "L36"}, {"id": "ems_swagger_testing_guide_step_4_paste_credentials_in_the_body", "label": "Step 4 \u2014 Paste credentials in the body", "file_type": "document", "source_file": "SWAGGER_TESTING_GUIDE.md", "source_location": "L40"}, {"id": "ems_swagger_testing_guide_step_5_click_execute", "label": "Step 5 \u2014 Click \"Execute\"", "file_type": "document", "source_file": "SWAGGER_TESTING_GUIDE.md", "source_location": "L54"}, {"id": "ems_swagger_testing_guide_step_6_copy_only_the_accesstoken_value", "label": "Step 6 \u2014 Copy ONLY the `accessToken` value", "file_type": "document", "source_file": "SWAGGER_TESTING_GUIDE.md", "source_location": "L62"}, {"id": "ems_swagger_testing_guide_step_7_scroll_up_click_the_green_authorize_button", "label": "Step 7 \u2014 Scroll up, click the green \"Authorize \ud83d\udd12\" button", "file_type": "document", "source_file": "SWAGGER_TESTING_GUIDE.md", "source_location": "L70"}, {"id": "ems_swagger_testing_guide_step_8_paste_the_token_in_the_bearer_field", "label": "Step 8 \u2014 Paste the token in the **Bearer** field", "file_type": "document", "source_file": "SWAGGER_TESTING_GUIDE.md", "source_location": "L74"}, {"id": "ems_swagger_testing_guide_step_9_click_authorize_under_the_bearer_row", "label": "Step 9 \u2014 Click \"Authorize\" under the Bearer row", "file_type": "document", "source_file": "SWAGGER_TESTING_GUIDE.md", "source_location": "L80"}, {"id": "ems_swagger_testing_guide_step_10_click_close", "label": "Step 10 \u2014 Click \"Close\"", "file_type": "document", "source_file": "SWAGGER_TESTING_GUIDE.md", "source_location": "L86"}, {"id": "ems_swagger_testing_guide_step_11_test_any_endpoint", "label": "Step 11 \u2014 Test any endpoint", "file_type": "document", "source_file": "SWAGGER_TESTING_GUIDE.md", "source_location": "L92"}, {"id": "ems_swagger_testing_guide_part_b_test_users_cheat_sheet", "label": "Part B \u2014 Test Users Cheat Sheet", "file_type": "document", "source_file": "SWAGGER_TESTING_GUIDE.md", "source_location": "L102"}, {"id": "ems_swagger_testing_guide_part_c_which_dashboard_endpoint_per_role", "label": "Part C \u2014 Which Dashboard Endpoint Per Role", "file_type": "document", "source_file": "SWAGGER_TESTING_GUIDE.md", "source_location": "L116"}, {"id": "ems_swagger_testing_guide_part_d_switching_between_roles", "label": "Part D \u2014 Switching Between Roles", "file_type": "document", "source_file": "SWAGGER_TESTING_GUIDE.md", "source_location": "L129"}, {"id": "ems_swagger_testing_guide_part_e_complete_endpoint_role_test_matrix", "label": "Part E \u2014 Complete Endpoint \u00d7 Role Test Matrix", "file_type": "document", "source_file": "SWAGGER_TESTING_GUIDE.md", "source_location": "L143"}, {"id": "ems_swagger_testing_guide_part_f_common_errors_and_fixes", "label": "Part F \u2014 Common Errors and Fixes", "file_type": "document", "source_file": "SWAGGER_TESTING_GUIDE.md", "source_location": "L207"}, {"id": "ems_swagger_testing_guide_part_g_postman_quick_start_alternative_to_swagger", "label": "Part G \u2014 Postman Quick Start (alternative to Swagger)", "file_type": "document", "source_file": "SWAGGER_TESTING_GUIDE.md", "source_location": "L220"}, {"id": "ems_swagger_testing_guide_part_h_where_to_find_more", "label": "Part H \u2014 Where to Find More", "file_type": "document", "source_file": "SWAGGER_TESTING_GUIDE.md", "source_location": "L231"}], "edges": [{"source": "users_mohdsaeedafri_all_code_base_ems_swagger_testing_guide_md", "target": "ems_swagger_testing_guide_ems_swagger_testing_guide", "relation": "contains", "confidence": "EXTRACTED", "source_file": "SWAGGER_TESTING_GUIDE.md", "source_location": "L1", "weight": 1.0}, {"source": "ems_swagger_testing_guide_ems_swagger_testing_guide", "target": "ems_swagger_testing_guide_test_result_production_verified_2026_05_19", "relation": "contains", "confidence": "EXTRACTED", "source_file": "SWAGGER_TESTING_GUIDE.md", "source_location": "L9", "weight": 1.0}, {"source": "ems_swagger_testing_guide_ems_swagger_testing_guide", "target": "ems_swagger_testing_guide_part_a_the_2_step_auth_flow_new_simpler", "relation": "contains", "confidence": "EXTRACTED", "source_file": "SWAGGER_TESTING_GUIDE.md", "source_location": "L22", "weight": 1.0}, {"source": "ems_swagger_testing_guide_part_a_the_2_step_auth_flow_new_simpler", "target": "ems_swagger_testing_guide_step_1_open_swagger_ui", "relation": "contains", "confidence": "EXTRACTED", "source_file": "SWAGGER_TESTING_GUIDE.md", "source_location": "L26", "weight": 1.0}, {"source": "ems_swagger_testing_guide_part_a_the_2_step_auth_flow_new_simpler", "target": "ems_swagger_testing_guide_step_2_find_post_auth_login_and_click_it_to_expand", "relation": "contains", "confidence": "EXTRACTED", "source_file": "SWAGGER_TESTING_GUIDE.md", "source_location": "L32", "weight": 1.0}, {"source": "ems_swagger_testing_guide_part_a_the_2_step_auth_flow_new_simpler", "target": "ems_swagger_testing_guide_step_3_click_try_it_out", "relation": "contains", "confidence": "EXTRACTED", "source_file": "SWAGGER_TESTING_GUIDE.md", "source_location": "L36", "weight": 1.0}, {"source": "ems_swagger_testing_guide_part_a_the_2_step_auth_flow_new_simpler", "target": "ems_swagger_testing_guide_step_4_paste_credentials_in_the_body", "relation": "contains", "confidence": "EXTRACTED", "source_file": "SWAGGER_TESTING_GUIDE.md", "source_location": "L40", "weight": 1.0}, {"source": "ems_swagger_testing_guide_part_a_the_2_step_auth_flow_new_simpler", "target": "ems_swagger_testing_guide_step_5_click_execute", "relation": "contains", "confidence": "EXTRACTED", "source_file": "SWAGGER_TESTING_GUIDE.md", "source_location": "L54", "weight": 1.0}, {"source": "ems_swagger_testing_guide_part_a_the_2_step_auth_flow_new_simpler", "target": "ems_swagger_testing_guide_step_6_copy_only_the_accesstoken_value", "relation": "contains", "confidence": "EXTRACTED", "source_file": "SWAGGER_TESTING_GUIDE.md", "source_location": "L62", "weight": 1.0}, {"source": "ems_swagger_testing_guide_part_a_the_2_step_auth_flow_new_simpler", "target": "ems_swagger_testing_guide_step_7_scroll_up_click_the_green_authorize_button", "relation": "contains", "confidence": "EXTRACTED", "source_file": "SWAGGER_TESTING_GUIDE.md", "source_location": "L70", "weight": 1.0}, {"source": "ems_swagger_testing_guide_part_a_the_2_step_auth_flow_new_simpler", "target": "ems_swagger_testing_guide_step_8_paste_the_token_in_the_bearer_field", "relation": "contains", "confidence": "EXTRACTED", "source_file": "SWAGGER_TESTING_GUIDE.md", "source_location": "L74", "weight": 1.0}, {"source": "ems_swagger_testing_guide_part_a_the_2_step_auth_flow_new_simpler", "target": "ems_swagger_testing_guide_step_9_click_authorize_under_the_bearer_row", "relation": "contains", "confidence": "EXTRACTED", "source_file": "SWAGGER_TESTING_GUIDE.md", "source_location": "L80", "weight": 1.0}, {"source": "ems_swagger_testing_guide_part_a_the_2_step_auth_flow_new_simpler", "target": "ems_swagger_testing_guide_step_10_click_close", "relation": "contains", "confidence": "EXTRACTED", "source_file": "SWAGGER_TESTING_GUIDE.md", "source_location": "L86", "weight": 1.0}, {"source": "ems_swagger_testing_guide_part_a_the_2_step_auth_flow_new_simpler", "target": "ems_swagger_testing_guide_step_11_test_any_endpoint", "relation": "contains", "confidence": "EXTRACTED", "source_file": "SWAGGER_TESTING_GUIDE.md", "source_location": "L92", "weight": 1.0}, {"source": "ems_swagger_testing_guide_ems_swagger_testing_guide", "target": "ems_swagger_testing_guide_part_b_test_users_cheat_sheet", "relation": "contains", "confidence": "EXTRACTED", "source_file": "SWAGGER_TESTING_GUIDE.md", "source_location": "L102", "weight": 1.0}, {"source": "ems_swagger_testing_guide_ems_swagger_testing_guide", "target": "ems_swagger_testing_guide_part_c_which_dashboard_endpoint_per_role", "relation": "contains", "confidence": "EXTRACTED", "source_file": "SWAGGER_TESTING_GUIDE.md", "source_location": "L116", "weight": 1.0}, {"source": "ems_swagger_testing_guide_ems_swagger_testing_guide", "target": "ems_swagger_testing_guide_part_d_switching_between_roles", "relation": "contains", "confidence": "EXTRACTED", "source_file": "SWAGGER_TESTING_GUIDE.md", "source_location": "L129", "weight": 1.0}, {"source": "ems_swagger_testing_guide_ems_swagger_testing_guide", "target": "ems_swagger_testing_guide_part_e_complete_endpoint_role_test_matrix", "relation": "contains", "confidence": "EXTRACTED", "source_file": "SWAGGER_TESTING_GUIDE.md", "source_location": "L143", "weight": 1.0}, {"source": "ems_swagger_testing_guide_ems_swagger_testing_guide", "target": "ems_swagger_testing_guide_part_f_common_errors_and_fixes", "relation": "contains", "confidence": "EXTRACTED", "source_file": "SWAGGER_TESTING_GUIDE.md", "source_location": "L207", "weight": 1.0}, {"source": "ems_swagger_testing_guide_ems_swagger_testing_guide", "target": "ems_swagger_testing_guide_part_g_postman_quick_start_alternative_to_swagger", "relation": "contains", "confidence": "EXTRACTED", "source_file": "SWAGGER_TESTING_GUIDE.md", "source_location": "L220", "weight": 1.0}, {"source": "ems_swagger_testing_guide_ems_swagger_testing_guide", "target": "ems_swagger_testing_guide_part_h_where_to_find_more", "relation": "contains", "confidence": "EXTRACTED", "source_file": "SWAGGER_TESTING_GUIDE.md", "source_location": "L231", "weight": 1.0}], "input_tokens": 0, "output_tokens": 0}